ctp_risk/__init__.py
ctp_risk/ctp_enum.py
ctp_risk/ctp_struct.py
ctp_risk/ctp_trade.py
ctp_risk/lib32/riskuserapi.dll
ctp_risk/lib64/libriskuserapi.so
ctp_risk/lib64/riskapi.so
ctp_risk/lib64/riskuserapi.dll
ctp_risk-0.0.8.1.data/data/README.md
ctp_risk-0.0.8.1.dist-info/METADATA
ctp_risk-0.0.8.1.dist-info/WHEEL
ctp_risk-0.0.8.1.dist-info/top_level.txt
ctp_risk-0.0.8.1.dist-info/RECORD
